{"updated_at":1777059420.3132744,"market_is_open":true,"next_open":"2026-04-27T09:30:00-04:00","next_close":"2026-04-24T16:00:00-04:00","api_calls_today":2981,"api_calls_total":2981,"mcp_alive":true,"rate_limited":false,"equity":105890.6,"cash":1499.65,"buying_power":246144.92,"day_pnl":-370.63,"day_pct":"-0.35","max_positions":12,"positions":[{"symbol":"BITO","qty":"1030.859","avg_entry_price":"10.48","current_price":"10.635","unrealized_pl":"159.783145","unrealized_plpc":"0.01479","market_value":"10963.185465"},{"symbol":"GE","qty":"27.074","avg_entry_price":"279.86","current_price":"284.01","unrealized_pl":"112.3571","unrealized_plpc":"0.01483","market_value":"7689.28674"},{"symbol":"MCK","qty":"9.061","avg_entry_price":"822.6","current_price":"826.3","unrealized_pl":"33.5257","unrealized_plpc":"0.0045","market_value":"7487.1043"},{"symbol":"META","qty":"15","avg_entry_price":"626.16","current_price":"676.65","unrealized_pl":"757.35","unrealized_plpc":"0.08063","market_value":"10149.75"},{"symbol":"MRVL","qty":"73.927","avg_entry_price":"152.87","current_price":"163.93","unrealized_pl":"817.63262","unrealized_plpc":"0.07235","market_value":"12118.85311"},{"symbol":"MU","qty":"14.995","avg_entry_price":"498.838002","current_price":"497.66","unrealized_pl":"-17.66414","unrealized_plpc":"-0.00236","market_value":"7462.4117"},{"symbol":"NVDA","qty":"36.571","avg_entry_price":"206.91","current_price":"208.485","unrealized_pl":"57.599325","unrealized_plpc":"0.00761","market_value":"7624.504935"},{"symbol":"QQQ","qty":"16","avg_entry_price":"605.22","current_price":"663.39","unrealized_pl":"930.72","unrealized_plpc":"0.09611","market_value":"10614.24"},{"symbol":"SEI","qty":"104.941","avg_entry_price":"71.01","current_price":"72.818","unrealized_pl":"189.733328","unrealized_plpc":"0.02546","market_value":"7641.593738"},{"symbol":"SNDK","qty":"7.838","avg_entry_price":"961.691375","current_price":"987.6499","unrealized_pl":"203.462919","unrealized_plpc":"0.02699","market_value":"7741.199916"},{"symbol":"STX","qty":"12.631","avg_entry_price":"579.49","current_price":"588.06","unrealized_pl":"108.24767","unrealized_plpc":"0.01479","market_value":"7427.78586"},{"symbol":"TSLA","qty":"19.798","avg_entry_price":"376.403746","current_price":"377.445","unrealized_pl":"20.614747","unrealized_plpc":"0.00277","market_value":"7472.65611"}],"trades":[{"ticker":"MU","side":"buy","qty":14.995,"entry_price":494.58000000000004,"stop_loss":469.85,"take_profit":544.04,"status":"orderstatus.filled","created_at":1777059286.8709173},{"ticker":"AAOI","side":"close","qty":47.158,"entry_price":160.8,"stop_loss":0.0,"take_profit":0.0,"status":"submitted","created_at":1777059085.5053527},{"ticker":"AAOI","side":"buy","qty":47.158,"entry_price":157.17000000000002,"stop_loss":149.31,"take_profit":172.89,"status":"orderstatus.filled","created_at":1777059082.6302955},{"ticker":"AMD","side":"close","qty":21.626,"entry_price":346.275,"stop_loss":0.0,"take_profit":0.0,"status":"submitted","created_at":1777058883.5202088},{"ticker":"AMD","side":"buy","qty":21.626,"entry_price":343.0,"stop_loss":325.85,"take_profit":377.3,"status":"orderstatus.filled","created_at":1777058880.4461188},{"ticker":"TSLA","side":"buy","qty":19.798,"entry_price":375.03,"stop_loss":356.28,"take_profit":412.53,"status":"orderstatus.filled","created_at":1777058548.1074693},{"ticker":"SOXL","side":"close","qty":57.946,"entry_price":128.51,"stop_loss":0.0,"take_profit":0.0,"status":"submitted","created_at":1777058350.433795},{"ticker":"AMD","side":"close","qty":21.667,"entry_price":346.02,"stop_loss":0.0,"take_profit":0.0,"status":"submitted","created_at":1777058349.084241},{"ticker":"AMD","side":"buy","qty":21.667,"entry_price":343.0,"stop_loss":325.85,"take_profit":377.3,"status":"orderstatus.filled","created_at":1777058278.4151535},{"ticker":"AMD","side":"close","qty":21.641,"entry_price":345.83,"stop_loss":0.0,"take_profit":0.0,"status":"submitted","created_at":1777058143.9422495},{"ticker":"AMD","side":"buy","qty":21.641,"entry_price":343.0,"stop_loss":325.85,"take_profit":377.3,"status":"orderstatus.filled","created_at":1777058076.9692926},{"ticker":"ASML","side":"close","qty":4.649,"entry_price":1465.89,"stop_loss":0.0,"take_profit":0.0,"status":"submitted","created_at":1777058074.704567},{"ticker":"ASML","side":"buy","qty":4.649,"entry_price":1596.155,"stop_loss":1516.35,"take_profit":1755.77,"status":"orderstatus.filled","created_at":1777058011.0084321},{"ticker":"AMD","side":"close","qty":21.634,"entry_price":345.1601,"stop_loss":0.0,"take_profit":0.0,"status":"submitted","created_at":1777057942.3972554},{"ticker":"AMD","side":"buy","qty":21.634,"entry_price":343.0,"stop_loss":325.85,"take_profit":377.3,"status":"orderstatus.filled","created_at":1777057878.0769448},{"ticker":"AMD","side":"close","qty":21.63,"entry_price":345.28,"stop_loss":0.0,"take_profit":0.0,"status":"submitted","created_at":1777057488.680041},{"ticker":"SOXL","side":"buy","qty":57.946,"entry_price":128.035,"stop_loss":121.63,"take_profit":140.84,"status":"orderstatus.filled","created_at":1777057487.313826},{"ticker":"ARM","side":"close","qty":31.876,"entry_price":234.19,"stop_loss":0.0,"take_profit":0.0,"status":"submitted","created_at":1777057221.2980242},{"ticker":"AMD","side":"buy","qty":21.63,"entry_price":343.0,"stop_loss":325.85,"take_profit":377.3,"status":"orderstatus.filled","created_at":1777057154.5869408},{"ticker":"AMD","side":"close","qty":21.624,"entry_price":346.47,"stop_loss":0.0,"take_profit":0.0,"status":"submitted","created_at":1777057027.7349706}],"signals":[{"ticker":"EBAY","direction":"bearish","source":"options_flow","size":48195.0,"score":0.46,"created_at":1777059420.161559},{"ticker":"MU","direction":"bearish","source":"options_flow","size":286500.0,"score":0.58,"created_at":1777059420.033184},{"ticker":"SOXL","direction":"bearish","source":"options_flow","size":13557.0,"score":0.51,"created_at":1777059419.8944194},{"ticker":"QQQ","direction":"bullish","source":"options_flow","size":255091.0,"score":0.58,"created_at":1777059419.7584276},{"ticker":"HTZ","direction":"bearish","source":"options_flow","size":42500.0,"score":0.46,"created_at":1777059419.6245577},{"ticker":"TSM","direction":"bearish","source":"insider","size":0.0,"score":0.384,"created_at":1777059357.4186463},{"ticker":"GRC","direction":"bullish","source":"insider","size":0.0,"score":0.384,"created_at":1777059357.2913058},{"ticker":"ABNB","direction":"bearish","source":"insider","size":1617281.46,"score":0.624,"created_at":1777059357.164337},{"ticker":"GL","direction":"bearish","source":"insider","size":5241780.0,"score":0.624,"created_at":1777059357.038731},{"ticker":"GL","direction":"bearish","source":"insider","size":7957477.54,"score":0.624,"created_at":1777059356.9130652},{"ticker":"AMZN","direction":"bearish","source":"insider","size":1000740.0,"score":0.624,"created_at":1777059356.7863975},{"ticker":"QQQ","direction":"bearish","source":"darkpool","size":101398.675,"score":0.579,"created_at":1777059356.6607344},{"ticker":"AAPL","direction":"bullish","source":"darkpool","size":272860.1,"score":0.579,"created_at":1777059356.5349836},{"ticker":"XOM","direction":"bullish","source":"darkpool","size":104758.5,"score":0.579,"created_at":1777059356.4113812},{"ticker":"APP","direction":"bullish","source":"darkpool","size":134068.228,"score":0.579,"created_at":1777059356.2873764},{"ticker":"BITO","direction":"bearish","source":"darkpool","size":238260.0,"score":0.579,"created_at":1777059356.1595478},{"ticker":"USFR","direction":"bullish","source":"darkpool","size":100880.2,"score":0.579,"created_at":1777059356.0313282},{"ticker":"CRWV","direction":"bearish","source":"darkpool","size":114452.0,"score":0.659,"created_at":1777059355.905226},{"ticker":"BITO","direction":"bearish","source":"darkpool","size":252339.0,"score":0.579,"created_at":1777059355.7793648},{"ticker":"GOOGL","direction":"bullish","source":"darkpool","size":135720.0,"score":0.579,"created_at":1777059355.6512146}]}