{"updated_at":1777303260.5904975,"market_is_open":true,"next_open":"2026-04-28T09:30:00-04:00","next_close":"2026-04-27T16:00:00-04:00","api_calls_today":3074,"api_calls_total":6631,"mcp_alive":true,"rate_limited":false,"equity":105280.92,"cash":661.64,"buying_power":278302.9,"day_pnl":-585.41,"day_pct":"-0.55","max_positions":12,"positions":[{"symbol":"AVGO","qty":"17.767","avg_entry_price":"415.25","current_price":"415.32","unrealized_pl":"1.24369","unrealized_plpc":"0.00017","market_value":"7378.99044"},{"symbol":"BITO","qty":"1030.859","avg_entry_price":"10.48","current_price":"10.5599","unrealized_pl":"82.365634","unrealized_plpc":"0.00762","market_value":"10885.767954"},{"symbol":"GE","qty":"27.074","avg_entry_price":"279.86","current_price":"280.765","unrealized_pl":"24.50197","unrealized_plpc":"0.00323","market_value":"7601.43161"},{"symbol":"MCK","qty":"9.061","avg_entry_price":"822.6","current_price":"828.975","unrealized_pl":"57.763875","unrealized_plpc":"0.00775","market_value":"7511.342475"},{"symbol":"META","qty":"15","avg_entry_price":"626.16","current_price":"677.765","unrealized_pl":"774.075","unrealized_plpc":"0.08242","market_value":"10166.475"},{"symbol":"MRVL","qty":"73.927","avg_entry_price":"152.87","current_price":"155.0475","unrealized_pl":"160.976043","unrealized_plpc":"0.01424","market_value":"11462.196533"},{"symbol":"NVDA","qty":"36.571","avg_entry_price":"203.280148","current_price":"209.715","unrealized_pl":"235.328972","unrealized_plpc":"0.03166","market_value":"7669.487265"},{"symbol":"OKLO","qty":"110.41","avg_entry_price":"71.283382","current_price":"71.86","unrealized_pl":"63.664393","unrealized_plpc":"0.00809","market_value":"7934.0626"},{"symbol":"QQQ","qty":"16","avg_entry_price":"605.22","current_price":"661.61","unrealized_pl":"902.24","unrealized_plpc":"0.09317","market_value":"10585.76"},{"symbol":"SNDK","qty":"7.838","avg_entry_price":"964.986963","current_price":"1049.638","unrealized_pl":"663.494828","unrealized_plpc":"0.08772","market_value":"8227.062644"},{"symbol":"STX","qty":"12.631","avg_entry_price":"579.49","current_price":"590.52","unrealized_pl":"139.31993","unrealized_plpc":"0.01903","market_value":"7458.85812"},{"symbol":"TEM","qty":"147.356","avg_entry_price":"51.989902","current_price":"52.52","unrealized_pl":"78.113121","unrealized_plpc":"0.0102","market_value":"7739.13712"}],"trades":[{"ticker":"AVGO","side":"buy","qty":17.767,"entry_price":416.7,"stop_loss":395.86,"take_profit":458.37,"status":"orderstatus.filled","created_at":1777301536.2239094},{"ticker":"SEI","side":"close","qty":104.941,"entry_price":70.365,"stop_loss":0.0,"take_profit":0.0,"status":"submitted","created_at":1777298023.6300263},{"ticker":"OKLO","side":"buy","qty":110.41,"entry_price":66.255,"stop_loss":62.94,"take_profit":72.88,"status":"orderstatus.filled","created_at":1777297951.7473178},{"ticker":"TSLA","side":"close","qty":19.798,"entry_price":366.521,"stop_loss":0.0,"take_profit":0.0,"status":"submitted","created_at":1777297881.6295037},{"ticker":"TEM","side":"buy","qty":147.356,"entry_price":50.34,"stop_loss":47.82,"take_profit":55.37,"status":"orderstatus.filled","created_at":1777296923.817288},{"ticker":"PLTR","side":"close","qty":51.751,"entry_price":143.2,"stop_loss":0.0,"take_profit":0.0,"status":"submitted","created_at":1777060469.2398784},{"ticker":"PLTR","side":"buy","qty":51.751,"entry_price":143.19,"stop_loss":136.03,"take_profit":157.51,"status":"orderstatus.filled","created_at":1777060467.4917378},{"ticker":"SPY","side":"close","qty":6.0,"entry_price":713.78,"stop_loss":0.0,"take_profit":0.0,"status":"submitted","created_at":1777060127.645194},{"ticker":"SPY","side":"buy","qty":10.371,"entry_price":714.165,"stop_loss":678.46,"take_profit":785.58,"status":"orderstatus.filled","created_at":1777060123.1424272},{"ticker":"MU","side":"close","qty":14.974,"entry_price":496.6,"stop_loss":0.0,"take_profit":0.0,"status":"submitted","created_at":1777060054.2659028},{"ticker":"MU","side":"buy","qty":14.974,"entry_price":494.58000000000004,"stop_loss":469.85,"take_profit":544.04,"status":"orderstatus.filled","created_at":1777059984.235628},{"ticker":"SPY","side":"close","qty":10.376,"entry_price":713.77,"stop_loss":0.0,"take_profit":0.0,"status":"submitted","created_at":1777059914.124741},{"ticker":"SPY","side":"buy","qty":10.376,"entry_price":714.165,"stop_loss":678.46,"take_profit":785.58,"status":"orderstatus.filled","created_at":1777059841.872222},{"ticker":"GOOGL","side":"close","qty":21.514,"entry_price":344.44,"stop_loss":0.0,"take_profit":0.0,"status":"submitted","created_at":1777059700.8909762},{"ticker":"GOOGL","side":"buy","qty":21.514,"entry_price":344.41999999999996,"stop_loss":327.2,"take_profit":378.86,"status":"orderstatus.filled","created_at":1777059630.2724905},{"ticker":"MU","side":"close","qty":14.995,"entry_price":497.52,"stop_loss":0.0,"take_profit":0.0,"status":"submitted","created_at":1777059488.4223988},{"ticker":"MU","side":"buy","qty":14.995,"entry_price":494.58000000000004,"stop_loss":469.85,"take_profit":544.04,"status":"orderstatus.filled","created_at":1777059286.8709173},{"ticker":"AAOI","side":"close","qty":47.158,"entry_price":160.8,"stop_loss":0.0,"take_profit":0.0,"status":"submitted","created_at":1777059085.5053527},{"ticker":"AAOI","side":"buy","qty":47.158,"entry_price":157.17000000000002,"stop_loss":149.31,"take_profit":172.89,"status":"orderstatus.filled","created_at":1777059082.6302955},{"ticker":"AMD","side":"close","qty":21.626,"entry_price":346.275,"stop_loss":0.0,"take_profit":0.0,"status":"submitted","created_at":1777058883.5202088}],"signals":[{"ticker":"CAR","direction":"bearish","source":"options_flow","size":20080.0,"score":0.46,"created_at":1777303260.4449642},{"ticker":"BE","direction":"bearish","source":"options_flow","size":129920.0,"score":0.58,"created_at":1777303260.3121443},{"ticker":"RVMD","direction":"bearish","source":"options_flow","size":20900.0,"score":0.46,"created_at":1777303260.183195},{"ticker":"NN","direction":"bullish","source":"options_flow","size":22500.0,"score":0.46,"created_at":1777303260.0548437},{"ticker":"IBIT","direction":"bullish","source":"options_flow","size":63000.0,"score":0.52,"created_at":1777303259.923801},{"ticker":"UBER","direction":"bearish","source":"insider","size":711526.76,"score":0.564,"created_at":1777303195.2191777},{"ticker":"VLY","direction":"bearish","source":"insider","size":1225870.98,"score":0.624,"created_at":1777303195.0940895},{"ticker":"TAL","direction":"bearish","source":"insider","size":1075207.16,"score":0.624,"created_at":1777303194.966409},{"ticker":"TWST","direction":"bearish","source":"insider","size":30915.0,"score":0.384,"created_at":1777303194.8345978},{"ticker":"KTOS","direction":"bearish","source":"insider","size":431480.0,"score":0.504,"created_at":1777303194.7073283},{"ticker":"UVSP","direction":"bearish","source":"insider","size":487630.0,"score":0.504,"created_at":1777303194.579986},{"ticker":"EQT","direction":"bearish","source":"insider","size":246136.8,"score":0.504,"created_at":1777303194.4521098},{"ticker":"TAL","direction":"bearish","source":"insider","size":48062.24,"score":0.384,"created_at":1777303194.3267226},{"ticker":"CHCO","direction":"bearish","source":"insider","size":297184.0,"score":0.504,"created_at":1777303194.200658},{"ticker":"TMO","direction":"bearish","source":"insider","size":185064.0,"score":0.504,"created_at":1777303194.0742974},{"ticker":"TEM","direction":"bullish","source":"darkpool","size":318790.08,"score":0.579,"created_at":1777303193.9458747},{"ticker":"MOH","direction":"bullish","source":"darkpool","size":201623.04,"score":0.579,"created_at":1777303193.816739},{"ticker":"W","direction":"bullish","source":"darkpool","size":101770.155,"score":0.579,"created_at":1777303193.6872127},{"ticker":"TXN","direction":"bullish","source":"darkpool","size":110450.0,"score":0.579,"created_at":1777303193.5602868},{"ticker":"TRV","direction":"bullish","source":"darkpool","size":128448.64,"score":0.579,"created_at":1777303193.4335592}]}